zenmav/__init__.py
zenmav/core.py
zenmav/test.py
zenmav/zenboundary.py
zenmav/zengimbal.py
zenmav/zenpoint.py
zenmav-0.1.8.dist-info/METADATA
zenmav-0.1.8.dist-info/WHEEL
zenmav-0.1.8.dist-info/top_level.txt
zenmav-0.1.8.dist-info/RECORD
