Metadata-Version: 2.4
Name: zenmav
Version: 0.1.8
Summary: Pymavlink wrappers for easy drone control developped by Zenith Polymtl
Author-email: Colin Rousseau <colin.rousseau@polymtl.ca>
License-Expression: Apache-2.0
Project-URL: Homepage, https://github.com/zenith-polymtl/Zenmav
Classifier: Programming Language :: Python :: 3
Classifier: Operating System :: OS Independent
Requires-Python: >=3.9
Requires-Dist: pymavlink
Requires-Dist: geopy
Requires-Dist: numpy
Requires-Dist: tomli
Requires-Dist: shapely
Requires-Dist: pyproj
Requires-Dist: matplotlib
Requires-Dist: pyserial
